{
  "$schema": "https://developer.microsoft.com/json-schemas/spfx/client-side-web-part-manifest.schema.json",
  "id": "654770e0-026b-41a9-8fc6-15d1c5466b8e",
  "alias": "CancelOrWithdrawalFormWebPart",
  "componentType": "WebPart",
  "version": "*",
  "manifestVersion": 2,
  "requiresCustomScript": false,
  "supportedHosts": ["SharePointWebPart", "SharePointFullPage"],
  "supportsThemeVariants": true,
  "preconfiguredEntries": [
    {
      "groupId": "5c03119e-3074-46fd-976b-c60198311f70",
      "group": { "default": "Advanced" },
      "title": { "default": "cancel-or-withdrawal-form" },
      "description": { "default": "cancel-or-withdrawal-form description" },
      "officeFabricIconFontName": "Page",
      "properties": {
        "description": "cancel-or-withdrawal-form"
      }
    }
  ]
}
